README.md
setup.py
pycqBot/__init__.py
pycqBot/asyncHttp.py
pycqBot/cqApi.py
pycqBot/cqCode.py
pycqBot/cqEvent.py
pycqBot/cqHttpApi.py
pycqBot/object.py
pycqBot.egg-info/PKG-INFO
pycqBot.egg-info/SOURCES.txt
pycqBot.egg-info/dependency_links.txt
pycqBot.egg-info/requires.txt
pycqBot.egg-info/top_level.txt
pycqBot/data/__init__.py
pycqBot/data/event.py
pycqBot/data/message.py
pycqBot/data/user.py
pycqBot/plugin/__init__.py
pycqBot/plugin/bilibili/__init__.py
pycqBot/plugin/bilibili/bilibili.py
pycqBot/plugin/manage/__init__.py
pycqBot/plugin/manage/manage.py
pycqBot/plugin/pixiv/__init__.py
pycqBot/plugin/pixiv/pixiv.py
pycqBot/plugin/test/__init__.py
pycqBot/plugin/test/test.py
pycqBot/plugin/twitter/__init__.py
pycqBot/plugin/twitter/twitter.py