Metadata-Version: 2.1
Name: pycqBot
Version: 0.5.1
Summary: go-cqhttp python 框架，可以用于快速塔建 bot
Home-page: https://github.com/FengLiuFeseliud/pycqBot
Author: FengLiuFeseliud
Author-email: 17351198406@qq.com
License: AGPL-3.0 License
Platform: any
Classifier: Programming Language :: Python :: 3
Classifier: Operating System :: OS Independent
Requires-Python: >=3.9
